{
  "version": "1.0.0",
  "restore": {
    "projectUniqueName": "C:\\Users\\devma\\RiderProjects\\MultiVendorRestaurantManagement\\MultiVendorRestaurantManagement\\MultiVendorRestaurantManagement.csproj",
    "projectName": "MultiVendorRestaurantManagement",
    "projectPath": "C:\\Users\\devma\\RiderProjects\\MultiVendorRestaurantManagement\\MultiVendorRestaurantManagement\\MultiVendorRestaurantManagement.csproj",
    "outputPath": "C:\\Users\\devma\\RiderProjects\\MultiVendorRestaurantManagement\\MultiVendorRestaurantManagement\\obj\\",
    "projectStyle": "PackageReference",
    "originalTargetFrameworks": [
      "netcoreapp3.1"
    ],
    "sources": {
      "C:\\Program Files (x86)\\Microsoft SDKs\\NuGetPackages\\": {},
      "https://api.nuget.org/v3/index.json": {}
    },
    "frameworks": {
      "netcoreapp3.1": {
        "projectReferences": {
          "C:\\Users\\devma\\RiderProjects\\MultiVendorRestaurantManagement\\Common\\Common.csproj": {
            "projectPath": "C:\\Users\\devma\\RiderProjects\\MultiVendorRestaurantManagement\\Common\\Common.csproj"
          },
          "C:\\Users\\devma\\RiderProjects\\MultiVendorRestaurantManagement\\MultiVendorRestaurantManagement.Domain\\MultiVendorRestaurantManagement.Domain.csproj": {
            "projectPath": "C:\\Users\\devma\\RiderProjects\\MultiVendorRestaurantManagement\\MultiVendorRestaurantManagement.Domain\\MultiVendorRestaurantManagement.Domain.csproj"
          }
        }
      }
    },
    "warningProperties": {
      "warnAsError": [
        "NU1605"
      ]
    }
  },
  "frameworks": {
    "netcoreapp3.1": {
      "dependencies": {
        "MediatR": {
          "target": "Package",
          "version": "[8.0.1, )"
        },
        "MediatR.Extensions.Microsoft.DependencyInjection": {
          "target": "Package",
          "version": "[8.0.0, )"
        },
        "Microsoft.EntityFrameworkCore.Design": {
          "target": "Package",
          "version": "[3.1.3, )"
        },
        "Microsoft.EntityFrameworkCore.SqlServer": {
          "target": "Package",
          "version": "[3.1.3, )"
        },
        "Swashbuckle.AspNetCore.Swagger": {
          "target": "Package",
          "version": "[5.4.0, )"
        },
        "Swashbuckle.AspNetCore.SwaggerGen": {
          "target": "Package",
          "version": "[5.4.0, )"
        },
        "Swashbuckle.AspNetCore.SwaggerUI": {
          "target": "Package",
          "version": "[5.4.0, )"
        }
      },
      "imports": [
        "net461",
        "net462",
        "net47",
        "net471",
        "net472",
        "net48"
      ],
      "assetTargetFallback": true,
      "warn": true,
      "frameworkReferences": {
        "Microsoft.AspNetCore.App": {
          "privateAssets": "none"
        },
        "Microsoft.NETCore.App": {
          "privateAssets": "all"
        }
      },
      "runtimeIdentifierGraphPath": "C:\\Program Files\\dotnet\\sdk\\3.1.201\\RuntimeIdentifierGraph.json"
    }
  }
}